consul_kv/__init__.py
consul_kv/api.py
consul_kv/serializer.py
consul_kv/settings.py
consul_kv/utils.py
consul_kv-0.7.4.dist-info/LICENSE.txt
consul_kv-0.7.4.dist-info/METADATA
consul_kv-0.7.4.dist-info/WHEEL
consul_kv-0.7.4.dist-info/top_level.txt
consul_kv-0.7.4.dist-info/RECORD
