Metadata-Version: 2.1
Name: consul_kv
Version: 0.7.4
Summary: Consul KV client for Python 3
Home-page: https://github.com/vdloo/consul-kv
Author: Rick van de Loo
Author-email: rickvandeloo@gmail.com
Keywords: consul,distributed,key,value
License-File: LICENSE.txt
